factory/__init__.py
factory/alchemy.py
factory/base.py
factory/builder.py
factory/declarations.py
factory/django.py
factory/enums.py
factory/errors.py
factory/faker.py
factory/fuzzy.py
factory/helpers.py
factory/mogo.py
factory/mongoengine.py
factory/random.py
factory/utils.py
factory_boy-3.3.2.dist-info/LICENSE
factory_boy-3.3.2.dist-info/METADATA
factory_boy-3.3.2.dist-info/WHEEL
factory_boy-3.3.2.dist-info/top_level.txt
factory_boy-3.3.2.dist-info/RECORD
